{
  "query": "SELECT * FROM negative_accounts LIMIT 20;",
  "command": "mysql --batch --raw --column-names --default-character-set=utf8mb4 --host gateway02.us-east-1.prod.aws.tidbcloud.com --port 4000 --user hzCbMda76tmFdt4.root --database KD8igV5APKrQwmz3rzYZ6D --execute SELECT * FROM negative_accounts LIMIT 20;",
  "rows": [
    {
      "id": "150001",
      "userId": "1",
      "accountName": "OAG CHILD SU",
      "accountNumber": "XXXX",
      "accountType": "Open account",
      "balance": "2552.00",
      "originalCreditor": "null",
      "dateOpened": "2023-12-17T05:00:00.000Z",
      "lastActivity": "2025-11-14T05:00:00.000Z",
      "status": "120 days past due",
      "transunionData": "NULL",
      "equifaxData": "NULL",
      "experianData": "NULL",
      "hasConflicts": "0",
      "conflictDetails": "NULL",
      "createdAt": "2026-01-08 21:55:01",
      "updatedAt": "2026-01-08 21:55:01"
    },
    {
      "id": "150002",
      "userId": "1",
      "accountName": "CU OF TX",
      "accountNumber": "531942XXXXXX",
      "accountType": "Revolving account",
      "balance": "3288.00",
      "originalCreditor": "null",
      "dateOpened": "2021-10-13T04:00:00.000Z",
      "lastActivity": "2025-11-25T05:00:00.000Z",
      "status": "Charged off as bad debt",
      "transunionData": "NULL",
      "equifaxData": "NULL",
      "experianData": "NULL",
      "hasConflicts": "0",
      "conflictDetails": "NULL",
      "createdAt": "2026-01-08 21:55:01",
      "updatedAt": "2026-01-08 21:55:01"
    },
    {
      "id": "150003",
      "userId": "1",
      "accountName": "FNWSE/OPPLNS",
      "accountNumber": "LAI036XXXXX",
      "accountType": "Installment account",
      "balance": "3749.00",
      "originalCreditor": "null",
      "dateOpened": "2024-04-03T04:00:00.000Z",
      "lastActivity": "2025-11-20T05:00:00.000Z",
      "status": "Charged off as bad debt",
      "transunionData": "NULL",
      "equifaxData": "NULL",
      "experianData": "NULL",
      "hasConflicts": "0",
      "conflictDetails": "NULL",
      "createdAt": "2026-01-08 21:55:01",
      "updatedAt": "2026-01-08 21:55:01"
    },
    {
      "id": "150004",
      "userId": "1",
      "accountName": "FRD MOTOR CR",
      "accountNumber": "607875XX",
      "accountType": "Installment account",
      "balance": "9770.00",
      "originalCreditor": "null",
      "dateOpened": "2021-12-09T05:00:00.000Z",
      "lastActivity": "2025-11-13T05:00:00.000Z",
      "status": "Charged off as bad debt",
      "transunionData": "NULL",
      "equifaxData": "NULL",
      "experianData": "NULL",
      "hasConflicts": "0",
      "conflictDetails": "NULL",
      "createdAt": "2026-01-08 21:55:01",
      "updatedAt": "2026-01-08 21:55:01"
    },
    {
      "id": "150005",
      "userId": "1",
      "accountName": "PRO COLLECT",
      "accountNumber": "517750XXXXXXXXX",
      "accountType": "Open account",
      "balance": "5614.00",
      "originalCreditor": "09 THE MANHATTAN APARTMENTS LUM",
      "dateOpened": "2025-02-20T05:00:00.000Z",
      "lastActivity": "2025-12-01T05:00:00.000Z",
      "status": "null",
      "transunionData": "NULL",
      "equifaxData": "NULL",
      "experianData": "NULL",
      "hasConflicts": "0",
      "conflictDetails": "NULL",
      "createdAt": "2026-01-08 21:55:01",
      "updatedAt": "2026-01-08 21:55:01"
    },
    {
      "id": "150006",
      "userId": "1",
      "accountName": "OAG CHILD SU",
      "accountNumber": "XXXX",
      "accountType": "Open account",
      "balance": "2552.00",
      "originalCreditor": "NULL",
      "dateOpened": "2023-12-17T05:00:00.000Z",
      "lastActivity": "2025-01-23T05:00:00.000Z",
      "status": "120 days past due",
      "transunionData": "NULL",
      "equifaxData": "NULL",
      "experianData": "NULL",
      "hasConflicts": "0",
      "conflictDetails": "NULL",
      "createdAt": "2026-01-08 21:55:21",
      "updatedAt": "2026-01-08 21:55:21"
    },
    {
      "id": "150007",
      "userId": "1",
      "accountName": "CU OF TX",
      "accountNumber": "531942XXXXXX",
      "accountType": "Revolving account",
      "balance": "3288.00",
      "originalCreditor": "NULL",
      "dateOpened": "2021-10-13T04:00:00.000Z",
      "lastActivity": "2025-09-12T04:00:00.000Z",
      "status": "Charged off as bad debt",
      "transunionData": "NULL",
      "equifaxData": "NULL",
      "experianData": "NULL",
      "hasConflicts": "0",
      "conflictDetails": "NULL",
      "createdAt": "2026-01-08 21:55:21",
      "updatedAt": "2026-01-08 21:55:21"
    },
    {
      "id": "150008",
      "userId": "1",
      "accountName": "FNWSE/OPPLNS",
      "accountNumber": "LAI036XXXXX",
      "accountType": "Installment account",
      "balance": "3749.00",
      "originalCreditor": "NULL",
      "dateOpened": "2024-04-03T04:00:00.000Z",
      "lastActivity": "2024-06-01T04:00:00.000Z",
      "status": "Charged off as bad debt",
      "transunionData": "NULL",
      "equifaxData": "NULL",
      "experianData": "NULL",
      "hasConflicts": "0",
      "conflictDetails": "NULL",
      "createdAt": "2026-01-08 21:55:21",
      "updatedAt": "2026-01-08 21:55:21"
    },
    {
      "id": "150009",
      "userId": "1",
      "accountName": "FRD MOTOR CR",
      "accountNumber": "607875XX",
      "accountType": "Installment account",
      "balance": "9770.00",
      "originalCreditor": "NULL",
      "dateOpened": "2021-12-09T05:00:00.000Z",
      "lastActivity": "2023-07-26T04:00:00.000Z",
      "status": "Charged off as bad debt",
      "transunionData": "NULL",
      "equifaxData": "NULL",
      "experianData": "NULL",
      "hasConflicts": "0",
      "conflictDetails": "NULL",
      "createdAt": "2026-01-08 21:55:21",
      "updatedAt": "2026-01-08 21:55:21"
    },
    {
      "id": "150010",
      "userId": "1",
      "accountName": "PRO COLLECT",
      "accountNumber": "517750XXXXXXXXX",
      "accountType": "Open account",
      "balance": "5614.00",
      "originalCreditor": "09 THE MANHATTAN APARTMENTS LUM",
      "dateOpened": "2025-02-20T05:00:00.000Z",
      "lastActivity": "2025-12-01T05:00:00.000Z",
      "status": "Collection",
      "transunionData": "NULL",
      "equifaxData": "NULL",
      "experianData": "NULL",
      "hasConflicts": "0",
      "conflictDetails": "NULL",
      "createdAt": "2026-01-08 21:55:21",
      "updatedAt": "2026-01-08 21:55:21"
    },
    {
      "id": "150011",
      "userId": "1",
      "accountName": "ATTORNEY GENERAL-CHI",
      "accountNumber": "137708XX",
      "accountType": "Open Account",
      "balance": "2552.00",
      "originalCreditor": "NULL",
      "dateOpened": "2023-12-17T05:00:00.000Z",
      "lastActivity": "2025-10-31T04:00:00.000Z",
      "status": "At least 120 days or more than four payments past due",
      "transunionData": "NULL",
      "equifaxData": "NULL",
      "experianData": "NULL",
      "hasConflicts": "0",
      "conflictDetails": "NULL",
      "createdAt": "2026-01-08 21:55:32",
      "updatedAt": "2026-01-08 21:55:32"
    },
    {
      "id": "150012",
      "userId": "1",
      "accountName": "CREDIT UNION OF TEXA",
      "accountNumber": "531942XXXXXXXXXX",
      "accountType": "Revolving",
      "balance": "3288.00",
      "originalCreditor": "NULL",
      "dateOpened": "2021-10-13T04:00:00.000Z",
      "lastActivity": "2025-11-25T05:00:00.000Z",
      "status": "Charge-off",
      "transunionData": "NULL",
      "equifaxData": "NULL",
      "experianData": "NULL",
      "hasConflicts": "0",
      "conflictDetails": "NULL",
      "createdAt": "2026-01-08 21:55:32",
      "updatedAt": "2026-01-08 21:55:32"
    },
    {
      "id": "150013",
      "userId": "1",
      "accountName": "FORD MOTOR CREDIT CO",
      "accountNumber": "607875XX",
      "accountType": "Installment",
      "balance": "9770.00",
      "originalCreditor": "NULL",
      "dateOpened": "2021-12-09T05:00:00.000Z",
      "lastActivity": "2025-11-08T05:00:00.000Z",
      "status": "Charge-off",
      "transunionData": "NULL",
      "equifaxData": "NULL",
      "experianData": "NULL",
      "hasConflicts": "0",
      "conflictDetails": "NULL",
      "createdAt": "2026-01-08 21:55:32",
      "updatedAt": "2026-01-08 21:55:32"
    },
    {
      "id": "150014",
      "userId": "1",
      "accountName": "OPPORTUNITY FINANCIA",
      "accountNumber": "LAI036XXXXX",
      "accountType": "Installment",
      "balance": "3749.00",
      "originalCreditor": "NULL",
      "dateOpened": "2024-04-03T04:00:00.000Z",
      "lastActivity": "2025-11-08T05:00:00.000Z",
      "status": "Charge-off",
      "transunionData": "NULL",
      "equifaxData": "NULL",
      "experianData": "NULL",
      "hasConflicts": "0",
      "conflictDetails": "NULL",
      "createdAt": "2026-01-08 21:55:32",
      "updatedAt": "2026-01-08 21:55:32"
    },
    {
      "id": "150015",
      "userId": "1",
      "accountName": "PROCOLLECT INC.",
      "accountNumber": "517750XXXXXXXXX",
      "accountType": "Collection Account",
      "balance": "5614.00",
      "originalCreditor": "THE MANHATTAN APARTMENTS LUM",
      "dateOpened": "2025-02-20T05:00:00.000Z",
      "lastActivity": "NULL",
      "status": "Unpaid",
      "transunionData": "NULL",
      "equifaxData": "NULL",
      "experianData": "NULL",
      "hasConflicts": "0",
      "conflictDetails": "NULL",
      "createdAt": "2026-01-08 21:55:32",
      "updatedAt": "2026-01-08 21:55:32"
    },
    {
      "id": "150016",
      "userId": "1",
      "accountName": "OFFICE OF THE ATTY GEN",
      "accountNumber": "137708XX",
      "accountType": "Child Support",
      "balance": "2552.00",
      "originalCreditor": "null",
      "dateOpened": "NULL",
      "lastActivity": "NULL",
      "status": "Open. $1,276 past due as of Nov 2025.",
      "transunionData": "NULL",
      "equifaxData": "NULL",
      "experianData": "NULL",
      "hasConflicts": "0",
      "conflictDetails": "NULL",
      "createdAt": "2026-01-08 21:55:49",
      "updatedAt": "2026-01-08 21:55:49"
    },
    {
      "id": "150017",
      "userId": "1",
      "accountName": "AFFIRM INC",
      "accountNumber": "HCEDVIXX",
      "accountType": "Unsecured",
      "balance": "1593.00",
      "originalCreditor": "null",
      "dateOpened": "NULL",
      "lastActivity": "NULL",
      "status": "Account charged off. $1,593 written off. $1,593 past due as of Dec 2025.",
      "transunionData": "NULL",
      "equifaxData": "NULL",
      "experianData": "NULL",
      "hasConflicts": "0",
      "conflictDetails": "NULL",
      "createdAt": "2026-01-08 21:55:49",
      "updatedAt": "2026-01-08 21:55:49"
    },
    {
      "id": "150018",
      "userId": "1",
      "accountName": "AFFIRM INC",
      "accountNumber": "KRI9VBXX",
      "accountType": "Unsecured",
      "balance": "3001.00",
      "originalCreditor": "null",
      "dateOpened": "NULL",
      "lastActivity": "NULL",
      "status": "Account charged off. $3,001 written off. $3,001 past due as of Dec 2025.",
      "transunionData": "NULL",
      "equifaxData": "NULL",
      "experianData": "NULL",
      "hasConflicts": "0",
      "conflictDetails": "NULL",
      "createdAt": "2026-01-08 21:55:49",
      "updatedAt": "2026-01-08 21:55:49"
    },
    {
      "id": "150019",
      "userId": "1",
      "accountName": "FORD MOTOR CREDIT COMP",
      "accountNumber": "607875XX",
      "accountType": "Auto Loan",
      "balance": "9770.00",
      "originalCreditor": "null",
      "dateOpened": "NULL",
      "lastActivity": "NULL",
      "status": "Account charged off. $42,512 written off. $9,770 past due as of Nov 2025.",
      "transunionData": "NULL",
      "equifaxData": "NULL",
      "experianData": "NULL",
      "hasConflicts": "0",
      "conflictDetails": "NULL",
      "createdAt": "2026-01-08 21:55:49",
      "updatedAt": "2026-01-08 21:55:49"
    },
    {
      "id": "150020",
      "userId": "1",
      "accountName": "OPPLOANS/FINWISE",
      "accountNumber": "LAI036XXXXX",
      "accountType": "Unsecured",
      "balance": "3749.00",
      "originalCreditor": "null",
      "dateOpened": "NULL",
      "lastActivity": "NULL",
      "status": "Account charged off. $3,749 written off. $3,749 past due as of Oct 2025.",
      "transunionData": "NULL",
      "equifaxData": "NULL",
      "experianData": "NULL",
      "hasConflicts": "0",
      "conflictDetails": "NULL",
      "createdAt": "2026-01-08 21:55:49",
      "updatedAt": "2026-01-08 21:55:49"
    }
  ],
  "messages": [],
  "stdout": "id\tuserId\taccountName\taccountNumber\taccountType\tbalance\toriginalCreditor\tdateOpened\tlastActivity\tstatus\ttransunionData\tequifaxData\texperianData\thasConflicts\tconflictDetails\tcreatedAt\tupdatedAt\n150001\t1\tOAG CHILD SU\tXXXX\tOpen account\t2552.00\tnull\t2023-12-17T05:00:00.000Z\t2025-11-14T05:00:00.000Z\t120 days past due\tNULL\tNULL\tNULL\t0\tNULL\t2026-01-08 21:55:01\t2026-01-08 21:55:01\n150002\t1\tCU OF TX\t531942XXXXXX\tRevolving account\t3288.00\tnull\t2021-10-13T04:00:00.000Z\t2025-11-25T05:00:00.000Z\tCharged off as bad debt\tNULL\tNULL\tNULL\t0\tNULL\t2026-01-08 21:55:01\t2026-01-08 21:55:01\n150003\t1\tFNWSE/OPPLNS\tLAI036XXXXX\tInstallment account\t3749.00\tnull\t2024-04-03T04:00:00.000Z\t2025-11-20T05:00:00.000Z\tCharged off as bad debt\tNULL\tNULL\tNULL\t0\tNULL\t2026-01-08 21:55:01\t2026-01-08 21:55:01\n150004\t1\tFRD MOTOR CR\t607875XX\tInstallment account\t9770.00\tnull\t2021-12-09T05:00:00.000Z\t2025-11-13T05:00:00.000Z\tCharged off as bad debt\tNULL\tNULL\tNULL\t0\tNULL\t2026-01-08 21:55:01\t2026-01-08 21:55:01\n150005\t1\tPRO COLLECT\t517750XXXXXXXXX\tOpen account\t5614.00\t09 THE MANHATTAN APARTMENTS LUM\t2025-02-20T05:00:00.000Z\t2025-12-01T05:00:00.000Z\tnull\tNULL\tNULL\tNULL\t0\tNULL\t2026-01-08 21:55:01\t2026-01-08 21:55:01\n150006\t1\tOAG CHILD SU\tXXXX\tOpen account\t2552.00\tNULL\t2023-12-17T05:00:00.000Z\t2025-01-23T05:00:00.000Z\t120 days past due\tNULL\tNULL\tNULL\t0\tNULL\t2026-01-08 21:55:21\t2026-01-08 21:55:21\n150007\t1\tCU OF TX\t531942XXXXXX\tRevolving account\t3288.00\tNULL\t2021-10-13T04:00:00.000Z\t2025-09-12T04:00:00.000Z\tCharged off as bad debt\tNULL\tNULL\tNULL\t0\tNULL\t2026-01-08 21:55:21\t2026-01-08 21:55:21\n150008\t1\tFNWSE/OPPLNS\tLAI036XXXXX\tInstallment account\t3749.00\tNULL\t2024-04-03T04:00:00.000Z\t2024-06-01T04:00:00.000Z\tCharged off as bad debt\tNULL\tNULL\tNULL\t0\tNULL\t2026-01-08 21:55:21\t2026-01-08 21:55:21\n150009\t1\tFRD MOTOR CR\t607875XX\tInstallment account\t9770.00\tNULL\t2021-12-09T05:00:00.000Z\t2023-07-26T04:00:00.000Z\tCharged off as bad debt\tNULL\tNULL\tNULL\t0\tNULL\t2026-01-08 21:55:21\t2026-01-08 21:55:21\n150010\t1\tPRO COLLECT\t517750XXXXXXXXX\tOpen account\t5614.00\t09 THE MANHATTAN APARTMENTS LUM\t2025-02-20T05:00:00.000Z\t2025-12-01T05:00:00.000Z\tCollection\tNULL\tNULL\tNULL\t0\tNULL\t2026-01-08 21:55:21\t2026-01-08 21:55:21\n150011\t1\tATTORNEY GENERAL-CHI\t137708XX\tOpen Account\t2552.00\tNULL\t2023-12-17T05:00:00.000Z\t2025-10-31T04:00:00.000Z\tAt least 120 days or more than four payments past due\tNULL\tNULL\tNULL\t0\tNULL\t2026-01-08 21:55:32\t2026-01-08 21:55:32\n150012\t1\tCREDIT UNION OF TEXA\t531942XXXXXXXXXX\tRevolving\t3288.00\tNULL\t2021-10-13T04:00:00.000Z\t2025-11-25T05:00:00.000Z\tCharge-off\tNULL\tNULL\tNULL\t0\tNULL\t2026-01-08 21:55:32\t2026-01-08 21:55:32\n150013\t1\tFORD MOTOR CREDIT CO\t607875XX\tInstallment\t9770.00\tNULL\t2021-12-09T05:00:00.000Z\t2025-11-08T05:00:00.000Z\tCharge-off\tNULL\tNULL\tNULL\t0\tNULL\t2026-01-08 21:55:32\t2026-01-08 21:55:32\n150014\t1\tOPPORTUNITY FINANCIA\tLAI036XXXXX\tInstallment\t3749.00\tNULL\t2024-04-03T04:00:00.000Z\t2025-11-08T05:00:00.000Z\tCharge-off\tNULL\tNULL\tNULL\t0\tNULL\t2026-01-08 21:55:32\t2026-01-08 21:55:32\n150015\t1\tPROCOLLECT INC.\t517750XXXXXXXXX\tCollection Account\t5614.00\tTHE MANHATTAN APARTMENTS LUM\t2025-02-20T05:00:00.000Z\tNULL\tUnpaid\tNULL\tNULL\tNULL\t0\tNULL\t2026-01-08 21:55:32\t2026-01-08 21:55:32\n150016\t1\tOFFICE OF THE ATTY GEN\t137708XX\tChild Support\t2552.00\tnull\tNULL\tNULL\tOpen. $1,276 past due as of Nov 2025.\tNULL\tNULL\tNULL\t0\tNULL\t2026-01-08 21:55:49\t2026-01-08 21:55:49\n150017\t1\tAFFIRM INC\tHCEDVIXX\tUnsecured\t1593.00\tnull\tNULL\tNULL\tAccount charged off. $1,593 written off. $1,593 past due as of Dec 2025.\tNULL\tNULL\tNULL\t0\tNULL\t2026-01-08 21:55:49\t2026-01-08 21:55:49\n150018\t1\tAFFIRM INC\tKRI9VBXX\tUnsecured\t3001.00\tnull\tNULL\tNULL\tAccount charged off. $3,001 written off. $3,001 past due as of Dec 2025.\tNULL\tNULL\tNULL\t0\tNULL\t2026-01-08 21:55:49\t2026-01-08 21:55:49\n150019\t1\tFORD MOTOR CREDIT COMP\t607875XX\tAuto Loan\t9770.00\tnull\tNULL\tNULL\tAccount charged off. $42,512 written off. $9,770 past due as of Nov 2025.\tNULL\tNULL\tNULL\t0\tNULL\t2026-01-08 21:55:49\t2026-01-08 21:55:49\n150020\t1\tOPPLOANS/FINWISE\tLAI036XXXXX\tUnsecured\t3749.00\tnull\tNULL\tNULL\tAccount charged off. $3,749 written off. $3,749 past due as of Oct 2025.\tNULL\tNULL\tNULL\t0\tNULL\t2026-01-08 21:55:49\t2026-01-08 21:55:49\n",
  "stderr": "",
  "execution_time_ms": 55
}